libkers/__init__.py
libkers/apiClient.py
libkers/breacher.py
libkers/intruder.py
libkers/ipParse.py
libkers/scanner.py
libkers/slagroom.py
libkers-0.0.2.2.dist-info/METADATA
libkers-0.0.2.2.dist-info/WHEEL
libkers-0.0.2.2.dist-info/top_level.txt
libkers-0.0.2.2.dist-info/RECORD
